BCD.v
module seg (BCD, seg);
input [3:0] BCD;
output [7:0] seg;
reg [7:0] seg;
always @(BCD) begin
    case (BCD)
        4'h0: seg = 8'hc0; 
        4'h1: seg = 8'hf9; 
        4'h2: seg = 8'ha4; 
        4'h3: seg = 8'hb0; 
        4'h4: seg = 8'h99; 
        4'h5: seg = 8'h92; 
        4'h6: seg = 8'h82; 
        4'h7: seg = 8'hf8; 
        4'h8: seg = 8'h80; 
        4'h9: seg = 8'h90; 
        default: seg = 8'hff;
    endcase
end
endmodule

module dff (clk, load, D, Din, Q);
input clk, D, Din, load;
output reg Q;
always@ (posedge clk) begin
    if (load) 
        Q = Din;
    else 
        Q = D;
end
endmodule


module BCD(clk, load, rst_syn, data, Q_out, seg_out);
input clk, rst_syn, load; 
input [3:0] data; 
output wire [3:0] Q_out;
reg Q0, Q1, Q2, Q3;

output wire [7:0] seg_out; 

dff dff0(.clk(clk), .load(load), .D(Q0), .Din(Q0), .Q(Q_out[0]));
dff dff1(.clk(clk), .load(load), .D(Q1), .Din(Q1), .Q(Q_out[1]));
dff dff2(.clk(clk), .load(load), .D(Q2), .Din(Q2), .Q(Q_out[2]));
dff dff3(.clk(clk), .load(load), .D(Q3), .Din(Q3), .Q(Q_out[3]));

always @(posedge clk) begin
    if (!rst_syn) begin
        Q0 = 0;
        Q1 = 0;
        Q2 = 0;
        Q3 = 0;
    end
    else if(load) begin
        Q0 <= data[0];
        Q1 <= data[1];
        Q2 <= data[2];
        Q3 <= data[3];
    end 
    else begin
        if (Q0 == 1 && Q3 == 1) begin
            Q0 = 0;
            Q3 = 0;
        end
        else begin
            Q0 <= ~Q0;
            Q1 <= (Q1 & ~Q0) | (~Q1 & Q0);
            Q2 <= (Q2 & ~Q1) | (Q2 & ~Q0) | (~Q2 & Q1 & Q0);
            Q3 <= (Q3) | (Q0 & Q1 & Q2);
        end
    end 
end

seg show_seg(Q_out, seg_out);

endmodule

testbench.v
`timescale 1ns/10ps
module BCD_tb;
reg clk;
reg rst_syn, load;
reg [3:0] data;
wire [3:0] Q_out;
wire [7:0] seg_out;

BCD BCD_tb(
    .clk(clk), 
    .load(load),
    .rst_syn(rst_syn),
    .data(data), 
    .Q_out(Q_out),
    .seg_out(seg_out)
);

initial begin
    clk = 1;
    rst_syn = 1;
    load = 1;
    data = 4'b0101;
end

always #50 clk = ~clk;


initial    #50 load = 1'b0;
initial    #400 load = 1'b1;
initial    #500 load = 1'b0;
initial    #300 rst_syn  = 1'b0;
initial    #400 rst_syn  = 1'b1;
initial    #2000 $finish;


initial begin
    $dumpfile("BCD.vcd");
    $dumpvars(0, BCD_tb);
end

endmodule

BCD.vcd
$date
	Thu May 05 15:13:23 2022
$end
$version
	Icarus Verilog
$end
$timescale
	10ps
$end
$scope module BCD_tb $end
$scope module BCD_tb $end
$var wire 1 ! clk $end
$var wire 4 " data [3:0] $end
$var wire 1 # load $end
$var wire 1 $ rst_syn $end
$var wire 8 % seg_out [7:0] $end
$var wire 4 & Q_out [3:0] $end
$var reg 1 ' Q0 $end
$var reg 1 ( Q1 $end
$var reg 1 ) Q2 $end
$var reg 1 * Q3 $end
$scope module dff0 $end
$var wire 1 ' D $end
$var wire 1 ' Din $end
$var wire 1 ! clk $end
$var wire 1 # load $end
$var reg 1 + Q $end
$upscope $end
$scope module dff1 $end
$var wire 1 ( D $end
$var wire 1 ( Din $end
$var wire 1 ! clk $end
$var wire 1 # load $end
$var reg 1 , Q $end
$upscope $end
$scope module dff2 $end
$var wire 1 ) D $end
$var wire 1 ) Din $end
$var wire 1 ! clk $end
$var wire 1 # load $end
$var reg 1 - Q $end
$upscope $end
$scope module dff3 $end
$var wire 1 * D $end
$var wire 1 * Din $end
$var wire 1 ! clk $end
$var wire 1 # load $end
$var reg 1 . Q $end
$upscope $end
$scope module show_seg $end
$var wire 4 / BCD [3:0] $end
$var reg 8 0 seg [7:0] $end
$upscope $end
$upscope $end
$upscope $end
$enddefinitions $end
#0
$dumpvars
bx 0
bx /
x.
x-
x,
x+
0*
1)
0(
1'
bx &
bx %
1$
1#
b101 "
1!
$end
#5000
0#
0!
#10000
1(
0'
b10010010 %
b10010010 0
0.
1-
0,
b101 &
b101 /
1+
1!
#15000
0!
#20000
1'
b10000010 %
b10000010 0
0+
b110 &
b110 /
1,
1!
#25000
0!
#30000
b11111000 %
b11111000 0
0)
0(
0'
b111 &
b111 /
1+
1!
0$
#35000
0!
#40000
1)
1'
b11000000 %
b11000000 0
0+
0,
b0 &
b0 /
0-
1!
1$
1#
#45000
0!
#50000
1(
0'
b10010010 %
b10010010 0
1-
b101 &
b101 /
1+
1!
0#
#55000
0!
#60000
1'
b10000010 %
b10000010 0
0+
b110 &
b110 /
1,
1!
#65000
0!
#70000
1*
0)
0(
0'
b11111000 %
b11111000 0
b111 &
b111 /
1+
1!
#75000
0!
#80000
1'
b10000000 %
b10000000 0
0+
0,
0-
b1000 &
b1000 /
1.
1!
#85000
0!
#90000
b10010000 %
b10010000 0
0*
0'
b1001 &
b1001 /
1+
1!
#95000
0!
#100000
1'
b11000000 %
b11000000 0
0+
b0 &
b0 /
0.
1!
#105000
0!
#110000
1(
0'
b11111001 %
b11111001 0
b1 &
b1 /
1+
1!
#115000
0!
#120000
1'
b10100100 %
b10100100 0
0+
b10 &
b10 /
1,
1!
#125000
0!
#130000
1)
0(
0'
b10110000 %
b10110000 0
b11 &
b11 /
1+
1!
#135000
0!
#140000
1'
b10011001 %
b10011001 0
0+
0,
b100 &
b100 /
1-
1!
#145000
0!
#150000
1(
0'
b10010010 %
b10010010 0
b101 &
b101 /
1+
1!
#155000
0!
#160000
1'
b10000010 %
b10000010 0
0+
b110 &
b110 /
1,
1!
#165000
0!
#170000
1*
0)
0(
0'
b11111000 %
b11111000 0
b111 &
b111 /
1+
1!
#175000
0!
#180000
1'
b10000000 %
b10000000 0
0+
0,
0-
b1000 &
b1000 /
1.
1!
#185000
0!
#190000
b10010000 %
b10010000 0
0*
0'
b1001 &
b1001 /
1+
1!
#195000
0!
#200000
1'
b11000000 %
b11000000 0
0+
b0 &
b0 /
0.
1!
